code_indexer_loop/__init__.py
code_indexer_loop/api.py
code_indexer_loop/code_splitter.py
code_indexer_loop/constants.py
code_indexer_loop/test_api.py
code_indexer_loop/test_api_dummy_file.py.txt
code_indexer_loop/test_api_dummy_sql.sql.txt
code_indexer_loop/utils.py
code_indexer_loop-0.2.1.dist-info/LICENSE
code_indexer_loop-0.2.1.dist-info/WHEEL
code_indexer_loop-0.2.1.dist-info/METADATA
code_indexer_loop-0.2.1.dist-info/RECORD
