Metadata-Version: 2.1
Name: code-indexer-loop
Version: 0.2.1
Summary: Code Indexer Loop
Author-email: Rick Lamers <rick@definitive.io>
Requires-Python: >=3.9
Requires-Dist: llama-index>=0.8.20,<0.9
Requires-Dist: chromadb>=0.4.8,<0.5
Requires-Dist: tree-sitter-languages>=1.7.0,<1.8
Requires-Dist: tree-sitter>=0.20.2,<0.21
Requires-Dist: tiktoken>=0.4.0,<0.5
Requires-Dist: langchain>=0.0.283
Requires-Dist: watchdog>=2.3.1,<2.4
Requires-Dist: nltk>=3.8.1,<3.9
Requires-Dist: toml ~=0.10.2 ; extra == "dev"
Requires-Dist: black ~=23.3.0 ; extra == "dev"
Requires-Dist: isort ~=5.9.3 ; extra == "dev"
Requires-Dist: autoflake ~=2.2.0 ; extra == "dev"
Requires-Dist: ruff ~=0.0.284 ; extra == "dev"
Requires-Dist: pytest ~=7.4.1 ; extra == "dev"
Requires-Dist: flit >=3.8.0,<4 ; extra == "dev"
Requires-Dist: pytest-cov ~=3.0.0 ; extra == "test"
Provides-Extra: dev
Provides-Extra: test
